odoo/addons/res_partner_journal_items_link/README.rst
odoo/addons/res_partner_journal_items_link/__init__.py
odoo/addons/res_partner_journal_items_link/__manifest__.py
odoo/addons/res_partner_journal_items_link/i18n/es.po
odoo/addons/res_partner_journal_items_link/i18n/res_partner_journal_items_link.pot
odoo/addons/res_partner_journal_items_link/readme/CONTRIBUTORS.rst
odoo/addons/res_partner_journal_items_link/readme/DESCRIPTION.rst
odoo/addons/res_partner_journal_items_link/static/description/icon.png
odoo/addons/res_partner_journal_items_link/static/description/index.html
odoo/addons/res_partner_journal_items_link/views/account_move_line.xml
odoo/addons/res_partner_journal_items_link/views/res_partner_view.xml
odoo_addon_res_partner_journal_items_link-15.0.1.0.0.6.dist-info/METADATA
odoo_addon_res_partner_journal_items_link-15.0.1.0.0.6.dist-info/WHEEL
odoo_addon_res_partner_journal_items_link-15.0.1.0.0.6.dist-info/top_level.txt
odoo_addon_res_partner_journal_items_link-15.0.1.0.0.6.dist-info/RECORD
